mrcnn/__init__.py
mrcnn/config.py
mrcnn/model.py
mrcnn/parallel_model.py
mrcnn/utils.py
mrcnn/visualize.py
mask_rcnn_12rics-0.2.3.dist-info/LICENSE
mask_rcnn_12rics-0.2.3.dist-info/METADATA
mask_rcnn_12rics-0.2.3.dist-info/WHEEL
mask_rcnn_12rics-0.2.3.dist-info/top_level.txt
mask_rcnn_12rics-0.2.3.dist-info/RECORD
